py3toolkit/__init__.py
py3toolkit/gen_supervisor_conf.py
py3toolkit/sshx.py
py3toolkit-0.2.4.dist-info/LICENSE
py3toolkit-0.2.4.dist-info/WHEEL
py3toolkit-0.2.4.dist-info/entry_points.txt
py3toolkit-0.2.4.dist-info/METADATA
py3toolkit-0.2.4.dist-info/RECORD
